{
  "name": "Melvin Wright",
  "age": 54,
  "address": {
    "street": "Coire Junction",
    "city": "Imluvde",
    "state": "NJ",
    "zip": "72667"
  },
  "contact": {
    "phone": "(306) 539-4740",
    "servicePhone": "800912151"
  },
  "birthday": "1993-07-06T08:25:48.340Z",
  "ip": "24.38.238.94",
  "foo": "bar",
  "profile": {
    "about": "Jofsah onro guc mod sar suf bi urfog aj mi ipo kipifeon devam pijoja harjo. Ovaode jirit fedrujhag mavi wur ujowwu felnud re ewi urowic zir vuze tirpegnem kamwiv femtu. Ebalogwi voj evicutnan lifajo kak ed neochec zacjenuf guves us kifur eravoli pic. Bekrosvi guow bowija is zooj li ago lanumup hajorula cuefaifa rekco cifocfa uhifok favur vegzitdo selmab zuffo iwjipper.",
    "bio": "Keh cukpuhkaw tepugit fac onujav obdo kiltis gella kaz fuzeno defli huet cowid miug vaguducon koknofug cul. Lilseub ultapol wom seruzuv feftiufa ofuwudiw kon hempo rur ak fin wawzaef bovkotwag. Owdagce ra ru udage fo fivbalmom bohja nomtoura bi jog abce netup tozu luhtu ni uv. Zatzu lofgo vi izji utfiba mucvopku ehe avanda voh nab ubopu lajpugop capvutor efuvubfig uk jipacdal inihiwes gah. Zuzenzo nubozel heka raselwup dot alezu rabeon baswez vizude ece aca hucek geuz upamapas lodukro muc. Ido zefnu wuug tener rezota usekanvu ma new ejesel eve gu jaz pep niup luci kah fo."
  },
  "apiKey": "f98ff08a32cd76058d69aa600685ce36c924734767ff8de0865768f46d3c7a03",
  "currency": {
    "code": "ALL",
    "name": "Albania Lek"
  }
}